{
  "args": {
    "exp_id": "smoke_indices",
    "random_seed": 42,
    "project": "aviramom-/ts-icl",
    "use_wandb": 0,
    "override_run": 1,
    "keys_to_match": [
      "exp_id",
      "random_seed",
      "method",
      "retrieval_strategies"
    ],
    "method": "random_baseline",
    "cache_dir": null,
    "quantization": null,
    "device": "cuda",
    "low_cpu_mem_usage": true,
    "batch_size": 1,
    "display_samples": 0,
    "qa_dataset_path": "qa_dataset.json",
    "retrieval_strategies": [
      "ts_only",
      "text_only",
      "fusion"
    ],
    "retrieval_k": [
      1
    ],
    "fusion_alpha": [
      0.25,
      0.5,
      0.75
    ],
    "n_splits": 1,
    "test_fraction": 0.1,
    "text_encoder": "all-MiniLM-L6-v2",
    "ts_max_len": 128,
    "model_type": "random_baseline",
    "max_seq_length": 4096,
    "max_new_tokens": 10,
    "format": "chat",
    "input_mode": "combined"
  },
  "summary": {
    "fusion_k1_a0.25": {
      "mean": 0.4305555555555556,
      "std": 0.0,
      "per_split": [
        0.4305555555555556
      ]
    },
    "fusion_k1_a0.50": {
      "mean": 0.3472222222222222,
      "std": 0.0,
      "per_split": [
        0.3472222222222222
      ]
    },
    "fusion_k1_a0.75": {
      "mean": 0.4444444444444444,
      "std": 0.0,
      "per_split": [
        0.4444444444444444
      ]
    },
    "text_only_k1": {
      "mean": 0.4166666666666667,
      "std": 0.0,
      "per_split": [
        0.4166666666666667
      ]
    },
    "ts_only_k1": {
      "mean": 0.4583333333333333,
      "std": 0.0,
      "per_split": [
        0.4583333333333333
      ]
    }
  }
}